shelvez/__init__.py
shelvez/serialer.py
shelvez/shelve.py
shelvez/sqlcache.py
shelvez/sqlite.py
shelvez/utils.py
shelvez/zstd.py
shelvez-0.4.3.dist-info/METADATA
shelvez-0.4.3.dist-info/WHEEL
shelvez-0.4.3.dist-info/RECORD
